pymps/__init__.py
pymps/dmrg.py
pymps/mps.py
pymps/version.py
pymps-0.0.1.dist-info/AUTHORS.md
pymps-0.0.1.dist-info/LICENSE
pymps-0.0.1.dist-info/METADATA
pymps-0.0.1.dist-info/WHEEL
pymps-0.0.1.dist-info/top_level.txt
pymps-0.0.1.dist-info/RECORD
